drf_orjson_renderer/__init__.py
drf_orjson_renderer/encoders.py
drf_orjson_renderer/parsers.py
drf_orjson_renderer/renderers.py
drf_orjson_renderer-1.7.3.dist-info/LICENSE
drf_orjson_renderer-1.7.3.dist-info/METADATA
drf_orjson_renderer-1.7.3.dist-info/WHEEL
drf_orjson_renderer-1.7.3.dist-info/top_level.txt
drf_orjson_renderer-1.7.3.dist-info/zip-safe
drf_orjson_renderer-1.7.3.dist-info/RECORD
