Metadata-Version: 2.1
Name: drf-orjson-renderer
Version: 1.7.3
Summary: Django RestFramework JSON Renderer Backed by orjson
Home-page: https://github.com/brianjbuck/drf_orjson_renderer
Author: brianjbuck
Author-email: brian@thebuckpasser.com
License: MIT
Keywords: drf_orjson_renderer,rest_framework,orjson
Classifier: Intended Audience :: Developers
Classifier: License :: OSI Approved :: MIT License
Classifier: Natural Language :: English
Classifier: Programming Language :: Python :: 3.7
Classifier: Programming Language :: Python :: 3.8
Classifier: Programming Language :: Python :: 3.9
Requires-Python: >=3.6.0
License-File: LICENSE
